{
  "main": {
    "id": "c85b291f0d15a14a",
    "type": "split",
    "children": [
      {
        "id": "f5c69bdfb9c09775",
        "type": "tabs",
        "children": [
          {
            "id": "1a3554c5b4bfee54",
            "type": "leaf",
            "state": {
              "type": "markdown",
              "state": {
                "file": "docs/Solution/解决方案目录.md",
                "mode": "source",
                "source": false
              }
            }
          }
        ]
      }
    ],
    "direction": "vertical"
  },
  "left": {
    "id": "6099d847468c82ec",
    "type": "split",
    "children": [
      {
        "id": "3150883969d17463",
        "type": "tabs",
        "children": [
          {
            "id": "238d3d554f94778b",
            "type": "leaf",
            "state": {
              "type": "file-explorer",
              "state": {
                "sortOrder": "alphabetical"
              }
            }
          },
          {
            "id": "50cd0eaee847d234",
            "type": "leaf",
            "state": {
              "type": "search",
              "state": {
                "query": "",
                "matchingCase": false,
                "explainSearch": false,
                "collapseAll": false,
                "extraContext": false,
                "sortOrder": "alphabetical"
              }
            }
          },
          {
            "id": "657ee0492f7ec475",
            "type": "leaf",
            "state": {
              "type": "bookmarks",
              "state": {}
            }
          }
        ]
      }
    ],
    "direction": "horizontal",
    "width": 300
  },
  "right": {
    "id": "8ae209e956e171a4",
    "type": "split",
    "children": [
      {
        "id": "36799978a74edf26",
        "type": "tabs",
        "children": [
          {
            "id": "8e6de8df35ddf90a",
            "type": "leaf",
            "state": {
              "type": "backlink",
              "state": {
                "file": "docs/Solution/解决方案目录.md",
                "collapseAll": true,
                "extraContext": false,
                "sortOrder": "alphabetical",
                "showSearch": false,
                "searchQuery": "",
                "backlinkCollapsed": false,
                "unlinkedCollapsed": true
              }
            }
          },
          {
            "id": "188a05456a6302be",
            "type": "leaf",
            "state": {
              "type": "outgoing-link",
              "state": {
                "file": "docs/Solution/解决方案目录.md",
                "linksCollapsed": false,
                "unlinkedCollapsed": true
              }
            }
          },
          {
            "id": "7351026b8d223f28",
            "type": "leaf",
            "state": {
              "type": "tag",
              "state": {
                "sortOrder": "frequency",
                "useHierarchy": true
              }
            }
          },
          {
            "id": "1f8c23780ff547ff",
            "type": "leaf",
            "state": {
              "type": "outline",
              "state": {
                "file": "docs/Solution/解决方案目录.md"
              }
            }
          }
        ],
        "currentTab": 3
      }
    ],
    "direction": "horizontal",
    "width": 300,
    "collapsed": true
  },
  "left-ribbon": {
    "hiddenItems": {
      "switcher:打开快速切换": false,
      "graph:查看关系图谱": false,
      "canvas:新建白板": false,
      "daily-notes:打开/创建今天的日记": false,
      "templates:插入模板": false,
      "command-palette:打开命令面板": false
    }
  },
  "active": "1a3554c5b4bfee54",
  "lastOpenFiles": [
    "docs/README.md",
    "docs/Solution/如何禁止使用ping命令.md",
    "docs/Solution/LVM-create.md",
    "docs/Solution/install-Chrome.md",
    "docs/Solution/CentOS停服解决方案.md",
    "docs/Solution/解决方案目录.md",
    "docs/res/Pasted image 20230505222159.png",
    "docs/res/Pasted image 20230505221915.png",
    "docs/res/Pasted image 20230505221643.png",
    "docs/Kylinsoft/银河麒麟桌面操作系统兼容适配.md",
    "docs/Kylinsoft/如何迁移到银河麒麟桌面操作系统.md",
    "docs/Solution/如何制作系统启动盘/README.md",
    "().md",
    "未命名.canvas",
    "docs/res/迁移流程.png",
    "docs/Kylinsoft/银河麒麟桌面操作系统.md",
    "docs/Kylinsoft/星光麒麟操作系统.md",
    "docs/Kylinsoft/银河麒麟高级服务器操作系统.md",
    "docs/Linux/CentOS.md",
    "docs/Linux/Linux.md",
    "docs/Linux/Linux-LVM.md",
    "docs/Linux/Linux系统启动过程.md",
    "docs/C/README.md",
    "docs/Solution/如何安装操作系统/README.md",
    "docs/操作系统/操作系统概述.md",
    "docs/操作系统/泛在操作系统.md",
    "docs/操作系统",
    "docs/Linux/git/README.md",
    "docs/Kylinsoft",
    "docs/新建文件夹",
    "未命名",
    "docs/Linux/kernel/Linux-Kernel.md",
    "docs/Python/改善Python程序的91个建议.md",
    "docs/Python/python编程规范.md",
    "res",
    "site/解决方案/操作系统安全加固/银河麒麟高级服务器操作系统V10/index.html",
    "site/解决方案/操作系统安全加固/中标麒麟高级服务器操作系统V7/index.html",
    "site/解决方案/操作系统安全加固/银河麒麟高级服务器操作系统V10",
    "site/解决方案/操作系统安全加固/中标麒麟高级服务器操作系统V7",
    "site/解决方案/操作系统安全加固",
    "site/css/fonts/fontawesome-webfont.svg",
    "site/res/解决方案/如何安装操作系统/安装银河麒麟桌面操作系统/9.png",
    "site/res/解决方案/如何安装操作系统/安装银河麒麟桌面操作系统/8.png",
    "site/res/解决方案/如何安装操作系统/安装银河麒麟桌面操作系统/7.png",
    "site/res/解决方案/如何安装操作系统/安装银河麒麟桌面操作系统/6.png",
    "site/res/解决方案/如何安装操作系统/安装银河麒麟桌面操作系统/5.png"
  ]
}